setup.py
logicmonitor_core/Collector.py
logicmonitor_core/Datasource.py
logicmonitor_core/Host.py
logicmonitor_core/HostList.py
logicmonitor_core/Hostgroup.py
logicmonitor_core/LogicMonitor.py
logicmonitor_core/Service.py
logicmonitor_core/__init__.py
logicmonitor_core.egg-info/PKG-INFO
logicmonitor_core.egg-info/SOURCES.txt
logicmonitor_core.egg-info/dependency_links.txt
logicmonitor_core.egg-info/not-zip-safe
logicmonitor_core.egg-info/requires.txt
logicmonitor_core.egg-info/top_level.txt