Metadata-Version: 1.0
Name: logicmonitor-core
Version: 1.0.7.4
Summary: LogicMonitor API python classes
Home-page: https://github.com/logicmonitor/lm_python
Author: LogicMonitor
Author-email: jeff.wozniak@logicmonitor.com
License: MIT
Keywords: LogicMonitor cloud monitoring infrastructure
Platform: UNKNOWN
